pyrxnorm.py
pyrxnorm-0.0.2.dist-info/LICENSE
pyrxnorm-0.0.2.dist-info/METADATA
pyrxnorm-0.0.2.dist-info/WHEEL
pyrxnorm-0.0.2.dist-info/top_level.txt
pyrxnorm-0.0.2.dist-info/RECORD
