Metadata-Version: 2.1
Name: pyrxnorm
Version: 0.0.2
Summary: Parse and use RxNorm in Python.
Author-email: Karel D'Oosterlinck <kareldoosterlinck@gmail.com>
Project-URL: Homepage, https://github.com/KarelDO/pyrxnorm
Project-URL: Bug Tracker, https://github.com/KarelDO/pyrxnorm/issues
Classifier: Programming Language :: Python :: 3
Classifier: License :: OSI Approved :: MIT License
Classifier: Operating System :: OS Independent
Requires-Python: >=3.9
License-File: LICENSE
Requires-Dist: pydantic (>=1.10.4)
Requires-Dist: pandas (>=1.5.3)
Requires-Dist: tqdm (>=4.64.1)
